{
  "main": {
    "id": "6121785ecff49aea",
    "type": "split",
    "children": [
      {
        "id": "08d0445040c1b19b",
        "type": "tabs",
        "dimension": 65.1270207852194,
        "children": [
          {
            "id": "63d3b481c00328d6",
            "type": "leaf",
            "pane-relief:history-v1": {
              "pos": 1,
              "stack": [
                {
                  "title": "Pnin",
                  "icon": "lucide-file",
                  "state": "{\"type\":\"markdown\",\"state\":{\"file\":\"1 notes/11 media/111 books/Pnin.md\",\"mode\":\"source\",\"source\":true}}",
                  "eState": "{\"cursor\":{\"from\":{\"line\":0,\"ch\":0},\"to\":{\"line\":0,\"ch\":0}}}"
                },
                {
                  "state": "{}",
                  "eState": "{}"
                },
                {
                  "title": "Scratchpad",
                  "icon": "lucide-file",
                  "state": "{\"type\":\"markdown\",\"state\":{\"file\":\"0 ttrpg/Scratchpad.md\",\"mode\":\"preview\",\"source\":true}}",
                  "eState": "{}"
                },
                {
                  "title": "ggmonstemplate",
                  "icon": "lucide-file",
                  "state": "{\"type\":\"markdown\",\"state\":{\"file\":\"obsidian.md/Templates/ggmonstemplate.md\",\"mode\":\"source\",\"source\":true}}",
                  "eState": "{\"cursor\":{\"from\":{\"line\":20,\"ch\":38},\"to\":{\"line\":20,\"ch\":68}}}"
                },
                {
                  "title": "z this is actually a really long title with lots of words so that it wraps",
                  "icon": "lucide-file",
                  "state": "{\"type\":\"markdown\",\"state\":{\"file\":\"z this is actually a really long title with lots of words so that it wraps.md\",\"mode\":\"preview\",\"source\":true}}",
                  "eState": "{}"
                },
                {
                  "title": "0 Books",
                  "icon": "lucide-file",
                  "state": "{\"type\":\"markdown\",\"state\":{\"file\":\"1 notes/11 media/0 Books.md\",\"mode\":\"preview\",\"source\":true}}",
                  "eState": "{}"
                }
              ]
            },
            "state": {
              "type": "markdown",
              "state": {
                "file": "1 notes/11 media/0 Books.md",
                "mode": "preview",
                "source": true
              }
            }
          },
          {
            "id": "b558578d75a51d86",
            "type": "leaf",
            "pane-relief:history-v1": {
              "pos": 0,
              "stack": [
                {
                  "state": "{}",
                  "eState": "{}"
                }
              ]
            },
            "state": {
              "type": "markdown",
              "state": {
                "file": "1 notes/11 media/111 books/Cat's Cradle.md",
                "mode": "source",
                "source": true
              }
            }
          },
          {
            "id": "f5ff61d01d156460",
            "type": "leaf",
            "pane-relief:history-v1": {
              "pos": 0,
              "stack": [
                {
                  "state": "{}",
                  "eState": "{}"
                }
              ]
            },
            "state": {
              "type": "markdown",
              "state": {
                "file": "1 notes/11 media/eating less meat - what I've learned.md",
                "mode": "preview",
                "source": true
              }
            },
            "group": "66a9a1bf77b65224"
          }
        ]
      },
      {
        "id": "a3562b9343667ca3",
        "type": "tabs",
        "dimension": 34.8729792147806,
        "children": [
          {
            "id": "c78acc9bb1a6005e",
            "type": "leaf",
            "pane-relief:history-v1": {
              "pos": 0,
              "stack": [
                {
                  "state": "{}",
                  "eState": "{}"
                }
              ]
            },
            "state": {
              "type": "markdown",
              "state": {
                "file": "1 notes/11 media/eating less meat - what I've learned.md",
                "mode": "preview",
                "source": true
              }
            },
            "group": "66a9a1bf77b65224"
          }
        ]
      }
    ],
    "direction": "vertical"
  },
  "left": {
    "id": "71ff5cef2bcbb103",
    "type": "split",
    "children": [
      {
        "id": "6b21e83ce3fccc7a",
        "type": "tabs",
        "dimension": 44.200626959247636,
        "children": [
          {
            "id": "5454cef8376b7ed7",
            "type": "leaf",
            "pane-relief:history-v1": {
              "pos": 0,
              "stack": [
                {
                  "state": "{}",
                  "eState": "{}"
                }
              ]
            },
            "state": {
              "type": "file-explorer",
              "state": {
                "sortOrder": "alphabetical"
              }
            }
          },
          {
            "id": "af1f2bf4f1765057",
            "type": "leaf",
            "state": {
              "type": "localgraph",
              "state": {
                "file": "1 notes/11 media/0 Books.md",
                "options": {
                  "collapse-filter": true,
                  "search": "",
                  "localJumps": 2,
                  "localBacklinks": true,
                  "localForelinks": true,
                  "localInterlinks": false,
                  "showTags": true,
                  "showAttachments": false,
                  "hideUnresolved": false,
                  "collapse-color-groups": true,
                  "colorGroups": [],
                  "collapse-display": false,
                  "showArrow": false,
                  "textFadeMultiplier": -3,
                  "nodeSizeMultiplier": 0.900333333333333,
                  "lineSizeMultiplier": 1,
                  "collapse-forces": false,
                  "centerStrength": 0.532564102564103,
                  "repelStrength": 0,
                  "linkStrength": 1,
                  "linkDistance": 250,
                  "scale": 0.6554983534946917,
                  "close": true
                }
              }
            }
          },
          {
            "id": "e0c1fa20ac4e5d0f",
            "type": "leaf",
            "state": {
              "type": "outline",
              "state": {
                "file": "1 notes/11 media/0 Books.md"
              }
            }
          }
        ]
      },
      {
        "id": "397bba701bd8cc32",
        "type": "tabs",
        "dimension": 55.799373040752364,
        "children": [
          {
            "id": "93f0b28a0d2319c1",
            "type": "leaf",
            "state": {
              "type": "tag",
              "state": {
                "sortOrder": "frequency",
                "useHierarchy": false
              }
            }
          },
          {
            "id": "6413b7954dbc144f",
            "type": "leaf",
            "state": {
              "type": "advanced-tables-toolbar",
              "state": {}
            }
          },
          {
            "id": "d697a6cc8aee9ec9",
            "type": "leaf",
            "state": {
              "type": "backlink",
              "state": {
                "file": "1 notes/11 media/0 Books.md",
                "collapseAll": true,
                "extraContext": false,
                "sortOrder": "alphabetical",
                "showSearch": false,
                "searchQuery": "",
                "backlinkCollapsed": false,
                "unlinkedCollapsed": true
              }
            }
          },
          {
            "id": "a4b1b546d28358b2",
            "type": "leaf",
            "state": {
              "type": "outline",
              "state": {
                "file": "1 notes/11 media/0 Books.md"
              }
            }
          },
          {
            "id": "a78cafa98ce6ae75",
            "type": "leaf",
            "state": {
              "type": "search",
              "state": {
                "query": "",
                "matchingCase": true,
                "explainSearch": false,
                "collapseAll": false,
                "extraContext": false,
                "sortOrder": "alphabetical"
              }
            }
          }
        ],
        "currentTab": 3
      }
    ],
    "direction": "horizontal",
    "width": 341.01499938964844
  },
  "right": {
    "id": "3ab63e9a8e394489",
    "type": "split",
    "children": [
      {
        "id": "2a64458d81cceb37",
        "type": "tabs",
        "children": [
          {
            "id": "1d1838dc8b31b0d0",
            "type": "leaf",
            "state": {
              "type": "localgraph",
              "state": {
                "file": "1 notes/11 media/0 Books.md",
                "options": {
                  "collapse-filter": false,
                  "search": "",
                  "localJumps": 2,
                  "localBacklinks": true,
                  "localForelinks": true,
                  "localInterlinks": false,
                  "showTags": false,
                  "showAttachments": false,
                  "hideUnresolved": false,
                  "collapse-color-groups": true,
                  "colorGroups": [],
                  "collapse-display": true,
                  "showArrow": false,
                  "textFadeMultiplier": -3,
                  "nodeSizeMultiplier": 1.0638636963987,
                  "lineSizeMultiplier": 1,
                  "collapse-forces": false,
                  "centerStrength": 1,
                  "repelStrength": 1.11825305978692,
                  "linkStrength": 1,
                  "linkDistance": 250,
                  "scale": 0.42967809143425173,
                  "close": true
                }
              }
            }
          },
          {
            "id": "37d0aa573942bc9a",
            "type": "leaf",
            "state": {
              "type": "outgoing-link",
              "state": {
                "file": "1 notes/11 media/0 Books.md",
                "linksCollapsed": false,
                "unlinkedCollapsed": true
              }
            }
          },
          {
            "id": "b5d467884939caa0",
            "type": "leaf",
            "state": {
              "type": "DICE_ROLLER_VIEW",
              "state": {}
            }
          }
        ]
      }
    ],
    "direction": "horizontal",
    "width": 374.21502685546875,
    "collapsed": true
  },
  "ribbon": {
    "mostRecentAction": ""
  },
  "active": "63d3b481c00328d6",
  "lastOpenFiles": [
    "1 notes/11 media/111 books/Pnin.md",
    "1 notes/11 media/0 Books.md",
    "1 notes/11 media/111 books/2666.md",
    "1 notes/11 media/111 books/Humboldt's Gift.md",
    "0 ttrpg/Scratchpad.md",
    "obsidian.md/Templates/ggmonstemplate.md",
    "0 ttrpg/Monsters.md",
    "z this is actually a really long title with lots of words so that it wraps.md",
    "1 notes/11 media/111 books/Cat's Cradle.md",
    "1 notes/11 media/eating less meat - what I've learned.md"
  ]
}